{
  "date": "2026-06-30",
  "mode": "prodaja",
  "source": "halo",
  "total_raw": 184,
  "total_unique": 61,
  "diff_new": [
    "1687563b4899",
    "2ebda0b7d4ad",
    "16355e2cddca",
    "3332229e0c3c",
    "2dd55665f511",
    "a5627a499a7e",
    "a1004a1e2789",
    "6193a63a43fd",
    "ac48e3c4b942",
    "8e4efa9ca1df",
    "df63bec19f72",
    "cdf22d055688",
    "dd93f8b9015d",
    "b3749f55cf8d",
    "f48451c20d9f",
    "fb31274e953f",
    "5c1fc181d900",
    "c36682d58ef2",
    "711c463256f5",
    "dfc8379c6905",
    "b253bd5599cb",
    "106ac5e97f07",
    "32d23e27029c",
    "d9b8141c4633",
    "7907a7fa8749",
    "068a46bc8973",
    "d82eaccc0454",
    "82ea7aa9f1a6",
    "33d3c2b4729d",
    "2bd0d9f203ce",
    "245cc5b94317",
    "32411e78bb20",
    "24a3071fc511",
    "b44ad9011937",
    "86fb55b63e3c",
    "e1ff9be4a250",
    "07d06f4675fc",
    "05bbf80adff6",
    "1bab5c690464",
    "0fbd87c35076",
    "e7758761dfe3",
    "4f81efca18ad",
    "8bce1214d7bb",
    "b9d31dfdbad7",
    "8c82e6fac9fb",
    "f8a02d730e17",
    "72435f35e936",
    "8d8a36da153d",
    "7e5199420215",
    "2418f15f83e6",
    "fb9190cc9d01",
    "dbada1990b14",
    "00835427e01d",
    "c02b778688f2",
    "3f9b26e03ea4",
    "ae39dd50e54f",
    "33b0135d7745",
    "aa36dc72d879",
    "2cb249633844",
    "be23052b70c8",
    "3f583eb46723"
  ],
  "diff_removed": [
    "66770d4777ef"
  ],
  "listings": [
    {
      "id": "32411e78bb20",
      "url": "https://www.halooglasi.com/nekretnine/prodaja-stanova/wellport-izuzetan-4-0-stan-u-prestiznom-kompl/5425647237026?kid=4",
      "naslov": "Naslov",
      "opis": "Moderan 4.0 stan, vrlo funkcionalnog rasporeda prostorija, južno orijentisan, sa obiljem dnevne svetlosti tokom celog dana. Prostorije: prostrani dnevni bo",
      "zgrada": "Wellport",
      "struktura": "4.0",
      "cena": 100000.0,
      "m2": null,
      "cena_m2": null,
      "agencija": null,
      "izvor": "halo"
    },
    {
      "id": "fb9190cc9d01",
      "url": "https://www.halooglasi.com/nekretnine/prodaja-stanova/soul-64-lux-neuseljavan-nov-garaza-id-25209/5425646699572?kid=4",
      "naslov": "Naslov",
      "opis": "Veoma luksuzan i kvalitetan stambeno-poslovni kompleks Soul 64, na izuzetnoj lokaciji - u blizini luksuznih naselja West 65, A blok, kao i poslovnog centra",
      "zgrada": "A Blok",
      "struktura": "ostalo",
      "cena": 100000.0,
      "m2": null,
      "cena_m2": null,
      "agencija": null,
      "izvor": "halo"
    },
    {
      "id": "2ebda0b7d4ad",
      "url": "https://www.halooglasi.com/nekretnine/prodaja-stanova/novo-soul-64-2-0-svetao-garaza-placen-pdv/5425646940053?kid=4",
      "naslov": "Naslov",
      "opis": "Soul 64 Novo, 2.0 na veoma traženoj lokaciji bez buke, u kvalitetnoj zgradi sa odličnom odličnom izolacijom ,odlično saobraćajno povezan, brz pristup na ve",
      "zgrada": "Soul 64",
      "struktura": "2.0",
      "cena": 100000.0,
      "m2": null,
      "cena_m2": null,
      "agencija": null,
      "izvor": "halo"
    },
    {
      "id": "a5627a499a7e",
      "url": "https://www.halooglasi.com/nekretnine/prodaja-stanova/airport-garden-54m2-garaza-uz-doplatu-odlican/5425647337270?kid=4",
      "naslov": "Naslov",
      "opis": "Airport Garden | Novi Beograd Vrednost nekretnine ne stvaraju zidovi. Stvaraju je ljudi koji žele da žive, rade i investiraju upravo na toj lokaciji. Zato ",
      "zgrada": "Airport Garden",
      "struktura": "ostalo",
      "cena": 100000.0,
      "m2": null,
      "cena_m2": null,
      "agencija": null,
      "izvor": "halo"
    },
    {
      "id": "1bab5c690464",
      "url": "https://www.halooglasi.com/nekretnine/prodaja-stanova/izuzetan-4-0-stan-od-106m2-wellport/5425646912665?kid=4",
      "naslov": "Naslov",
      "opis": "Izuzetan četvorosoban stan površine 106m2 u bloku 65, u kompleksu Wellport, u ulici Tadije Sondermajera na 2. spratu. Dnevni boravak, kuhinja sa trpezarijo",
      "zgrada": "Wellport",
      "struktura": "4.0",
      "cena": 100000.0,
      "m2": 106.0,
      "cena_m2": 943,
      "agencija": null,
      "izvor": "halo"
    },
    {
      "id": "2418f15f83e6",
      "url": "https://www.halooglasi.com/nekretnine/prodaja-stanova/dvosoban-stan-belvil/5425647332451?kid=4",
      "naslov": "Naslov",
      "opis": "Prodaje se uknjižen dvosoban stan od 56m2 u naselju Belvil, na Novom Beogradu. Stan se nalazi na 1. spratu zgrade od 10 spratova, sa dva lifta. Stan nema t",
      "zgrada": "Belvil",
      "struktura": "2.0",
      "cena": 100000.0,
      "m2": 56.0,
      "cena_m2": 1786,
      "agencija": null,
      "izvor": "halo"
    },
    {
      "id": "a1004a1e2789",
      "url": "https://www.halooglasi.com/nekretnine/prodaja-stanova/west-65-nov-atraktivan-3-0-stan/5425645741098?kid=4",
      "naslov": "Naslov",
      "opis": "U prestižnom naselju na Novom Beogradu, West 65, koji je izvanredan primer spoja savremene umetnosti i arhitekture, nalazi se ovaj trosoban stan. Impresivn",
      "zgrada": "West 65",
      "struktura": "3.0",
      "cena": 100000.0,
      "m2": null,
      "cena_m2": null,
      "agencija": null,
      "izvor": "halo"
    },
    {
      "id": "df63bec19f72",
      "url": "https://www.halooglasi.com/nekretnine/prodaja-stanova/moderan-stan-u-prestiznom-kompleksu-airport-g/5425647299225?kid=4",
      "naslov": "Naslov",
      "opis": "Moderan stan u jednom od najtraženijih kompleksa na Novom Beogradu Prodaje se potpuno nov, neuseljavan jednosoban stan površine 32 m² u prestižnom kompleks",
      "zgrada": "Airport Garden",
      "struktura": "garsonjera",
      "cena": 100000.0,
      "m2": 32.0,
      "cena_m2": 3125,
      "agencija": null,
      "izvor": "halo"
    },
    {
      "id": "16355e2cddca",
      "url": "https://www.halooglasi.com/nekretnine/prodaja-stanova/blok-65---tadije-sondermajera-penthouse-107m2/5425647293490?kid=4",
      "naslov": "Naslov",
      "opis": "U luksuznom stambeno-poslovnom objektu ZepTerra, na 9. spratu, prodajemo penthouse ukupne površine 107m2. Stan je moderno koncipiran, sa velikim dnevnim bo",
      "zgrada": "Zepterra",
      "struktura": "ostalo",
      "cena": 100000.0,
      "m2": 107.0,
      "cena_m2": 935,
      "agencija": null,
      "izvor": "halo"
    },
    {
      "id": "b44ad9011937",
      "url": "https://www.halooglasi.com/nekretnine/prodaja-stanova/ekskluzivna-prodaja-west-65-kula-97m2-delux-g/5425646674441?kid=4",
      "naslov": "Naslov",
      "opis": "Delux, magičnih 97m2 stan, panoramskog pogleda, dizajnerski opremljen prostor koji je u višegodišnjem zakupu i zakupac je opredeljen da nastavi dugoročni z",
      "zgrada": "West 65 Kula",
      "struktura": "ostalo",
      "cena": 100000.0,
      "m2": 97.0,
      "cena_m2": 1031,
      "agencija": null,
      "izvor": "halo"
    },
    {
      "id": "7907a7fa8749",
      "url": "https://www.halooglasi.com/nekretnine/prodaja-stanova/novi-beograd---savada---3-0-id24923/5425646973207?kid=3",
      "naslov": "Naslov",
      "opis": "Stan se nalazi na jednoj od prestižnih lokacija Novog Beograda u Savadi, povučen od ulice, ušuškan u parkovskom okruženju, u zgradi koja je uredna, besprek",
      "zgrada": "Savada",
      "struktura": "3.0",
      "cena": 100000.0,
      "m2": null,
      "cena_m2": null,
      "agencija": null,
      "izvor": "halo"
    },
    {
      "id": "3f583eb46723",
      "url": "https://www.halooglasi.com/nekretnine/prodaja-stanova/airport-garden-55-m-garazno-mesto-vrhunska-no/5425647329704?kid=3",
      "naslov": "Naslov",
      "opis": " AIRPORT GARDEN – NOVOGRADNJA KOJA PRUŽA VIŠE OD STANA U ponudi je moderan stan površine 55 m² sa pripadajućim parking mestom od 13 m² na nivou -2 garaže .",
      "zgrada": "Airport Garden",
      "struktura": "ostalo",
      "cena": 100000.0,
      "m2": 55.0,
      "cena_m2": 1818,
      "agencija": null,
      "izvor": "halo"
    },
    {
      "id": "82ea7aa9f1a6",
      "url": "https://www.halooglasi.com/nekretnine/prodaja-stanova/komforan-namesten-trosoban-stan-u-belvilu-106/5425645129726?kid=3",
      "naslov": "Naslov",
      "opis": "Komforan trosoban stan uknjižen na 106m2, nalazi se u kompleksu Belvil, zgrada Ciklama. Stan je trostrano orijentisan, svetao sa otvorenim pogledom na ok",
      "zgrada": "Belvil",
      "struktura": "3.0",
      "cena": 100000.0,
      "m2": 106.0,
      "cena_m2": 943,
      "agencija": null,
      "izvor": "halo"
    },
    {
      "id": "24a3071fc511",
      "url": "https://www.halooglasi.com/nekretnine/prodaja-stanova/airport-garden-nov-neuseljavan/5425646880029?kid=3",
      "naslov": "Naslov",
      "opis": "Луксузан двособан стан од 60 m² у престижном комплексу Airport Garden, у Блоку 65. Стан се налази на четвртом спрату модерне новоградње, двострано је орије",
      "zgrada": "Airport Garden",
      "struktura": "ostalo",
      "cena": 100000.0,
      "m2": 60.0,
      "cena_m2": 1667,
      "agencija": null,
      "izvor": "halo"
    },
    {
      "id": "0fbd87c35076",
      "url": "https://www.halooglasi.com/nekretnine/prodaja-stanova/soul-64-86m-luksuzan-kompleks/5425647174486?kid=3",
      "naslov": "Naslov",
      "opis": "U ponudi je luksuzan trosoban stan površine 86,07m² u ekskluzivnom kompleksu SOUL 64, jednom od najmodernijih i najkvalitetnijih stambenih projekata u grad",
      "zgrada": "Soul 64",
      "struktura": "3.0",
      "cena": 100000.0,
      "m2": 7.0,
      "cena_m2": 14286,
      "agencija": null,
      "izvor": "halo"
    },
    {
      "id": "d9b8141c4633",
      "url": "https://www.halooglasi.com/nekretnine/prodaja-stanova/novi-beograd---blok-65---savada/5425646871677?kid=3",
      "naslov": "Naslov",
      "opis": "Na prodaju dvosoban stan površine 52 m² u zgradi Savada 3 u Bloku 65 na Novom Beogradu. Stan se nalazi na 10/10 spratu u zgradi sa liftom. Funkcionalnog je",
      "zgrada": "Savada",
      "struktura": "2.0",
      "cena": 100000.0,
      "m2": 52.0,
      "cena_m2": 1923,
      "agencija": null,
      "izvor": "halo"
    },
    {
      "id": "b9d31dfdbad7",
      "url": "https://www.halooglasi.com/nekretnine/prodaja-stanova/top-lokacija-zepterra-108m2-lux-stan-id2118/5425647235090?kid=3",
      "naslov": "Naslov",
      "opis": "U ponudi je izuzetan trosoban stan površine 108 m², smešten u prestižnom kompleksu Zeptterra, koji predstavlja spoj savremenog dizajna, komfora i privatnos",
      "zgrada": "Zepterra",
      "struktura": "3.0",
      "cena": 100000.0,
      "m2": 108.0,
      "cena_m2": 926,
      "agencija": null,
      "izvor": "halo"
    },
    {
      "id": "6193a63a43fd",
      "url": "https://www.halooglasi.com/nekretnine/prodaja-stanova/blok-21-trosoban-bez-ulaganja/5425647347771?kid=1",
      "naslov": "Naslov",
      "opis": "Odličan trosoban stan 76m2, Blok 21 Kompletno renoviran, uknjižen, odmah useljiv! Prodaje se trosoban stan, uknjižene korisne površine 76m² na jednoj od na",
      "zgrada": "A Blok",
      "struktura": "3.0",
      "cena": 100000.0,
      "m2": 76.0,
      "cena_m2": 1316,
      "agencija": null,
      "izvor": "halo"
    },
    {
      "id": "068a46bc8973",
      "url": "https://www.halooglasi.com/nekretnine/prodaja-stanova/west-tower-blok-65-lux-stan/5425647051438?kid=1",
      "naslov": "Naslov",
      "opis": "Predstavljamo Vam ekskluzivan luksuzan stan na prestižnoj lokaciji- West 65, Novi Beograd. Ovaj impresivan trosoban stan površine 95m2, dizajniran je sa po",
      "zgrada": "West 65",
      "struktura": "3.0",
      "cena": 100000.0,
      "m2": 95.0,
      "cena_m2": 1053,
      "agencija": null,
      "izvor": "halo"
    },
    {
      "id": "dd93f8b9015d",
      "url": "https://www.halooglasi.com/nekretnine/prodaja-stanova/lux-komforan-svetao/5425647078306?kid=1",
      "naslov": "Naslov",
      "opis": "U ponudi je svetao i komforan četvorosoban stan u okviru novoizgradjenog kompleksa “Lastavica”. Prilikom izgradnje a po planu arhitekte napravljena je kuhi",
      "zgrada": "Lastavica",
      "struktura": "4.0",
      "cena": 100000.0,
      "m2": null,
      "cena_m2": null,
      "agencija": null,
      "izvor": "halo"
    },
    {
      "id": "f48451c20d9f",
      "url": "https://www.halooglasi.com/nekretnine/prodaja-stanova/novi-beograd-belvil-2-0-odmah-useljiv-uknjize/5425646964953?kid=1",
      "naslov": "Naslov",
      "opis": "Novi Beograd, Belvil, dvosoban, odmah useljiv, uknj .. / stan pogodan i za dnevno izdavanje, Belvil, Blok 67, Đorđa Stanojevića, zgrada Šeboj, funkcionalan",
      "zgrada": "Belvil",
      "struktura": "2.0",
      "cena": 100000.0,
      "m2": null,
      "cena_m2": null,
      "agencija": null,
      "izvor": "halo"
    },
    {
      "id": "aa36dc72d879",
      "url": "https://www.halooglasi.com/nekretnine/prodaja-stanova/wellport-blok-65---trosoban-stan-75m/5425647342116?kid=1",
      "naslov": "Naslov",
      "opis": "Dvostrano orijentisan trosoban stan u okviru Wellport kompleksa, površine 75m², rađen po projektu poznatog beogradskog arhitektonskog studija. Projektovan ",
      "zgrada": "Wellport",
      "struktura": "3.0",
      "cena": 100000.0,
      "m2": 75.0,
      "cena_m2": 1333,
      "agencija": null,
      "izvor": "halo"
    },
    {
      "id": "05bbf80adff6",
      "url": "https://www.halooglasi.com/nekretnine/prodaja-stanova/odlican-2-5-stan-od-75-62m2-sakura-park/5425646962262?kid=1",
      "naslov": "Naslov",
      "opis": "Odličan dvoiposoban stan površine 75,62m2 u novoizgrađenom kompleksu Sakura Park, preko puta naselja Belville i TC Delta City. Dnevni boravak, kuhinja sa t",
      "zgrada": "Belvil",
      "struktura": "2.5",
      "cena": 100000.0,
      "m2": 62.0,
      "cena_m2": 1613,
      "agencija": null,
      "izvor": "halo"
    },
    {
      "id": "33d3c2b4729d",
      "url": "https://www.halooglasi.com/nekretnine/prodaja-stanova/novi-beograd-belville---bulevar-crvene-armije/5425644704505?kid=1",
      "naslov": "Naslov",
      "opis": "Novi Beograd, Belville - Bulevar Crvene Armije 94m2 4.0, 94m2 (terasa), 13/13, CG, lift, internet, interfon, dve klime, ktv,video nadzor, garažno mesto. No",
      "zgrada": "Belvil",
      "struktura": "4.0",
      "cena": 100000.0,
      "m2": 94.0,
      "cena_m2": 1064,
      "agencija": null,
      "izvor": "halo"
    },
    {
      "id": "b253bd5599cb",
      "url": "https://www.halooglasi.com/nekretnine/prodaja-stanova/blok-22-95m2-40m2-tavanski-prostor-135m-id117/5425645847228?kid=1",
      "naslov": "Naslov",
      "opis": "Funkcionalan, četvorosoban stan, uknjižene površine 95m2, korisne površine 135m2 - iz dnevnog boravka se izlazi u potkrovlje površine 40m2 open-space. Nala",
      "zgrada": "A Blok",
      "struktura": "4.0",
      "cena": 100000.0,
      "m2": 95.0,
      "cena_m2": 1053,
      "agencija": null,
      "izvor": "halo"
    },
    {
      "id": "8c82e6fac9fb",
      "url": "https://www.halooglasi.com/nekretnine/prodaja-stanova/soul-64-ekskluzivno-nov-neuseljen-stan/5425647076857?kid=1",
      "naslov": "Naslov",
      "opis": "Komforan dvosoban stan od 55m2, sa odličnim rasporedom: prostrana dnevna soba, odvojena kuhinja, spavaća soba (11m2), kupatilo i odvojen servis (za bojler,",
      "zgrada": "Soul 64",
      "struktura": "2.0",
      "cena": 100000.0,
      "m2": 55.0,
      "cena_m2": 1818,
      "agencija": null,
      "izvor": "halo"
    },
    {
      "id": "711c463256f5",
      "url": "https://www.halooglasi.com/nekretnine/prodaja-stanova/delta-city-lastavica---jurija-gagarina/5425646795123?kid=1",
      "naslov": "Naslov",
      "opis": "Novi Beograd, Delta city (Lastavica) - Jurija Gagarina 2.0, 62m2 (terasa 5m2), 2/6, CG, lift, telefon, interfon, parking U podudi stan u luksuznoj novograd",
      "zgrada": "Lastavica",
      "struktura": "2.0",
      "cena": 100000.0,
      "m2": 62.0,
      "cena_m2": 1613,
      "agencija": null,
      "izvor": "halo"
    },
    {
      "id": "245cc5b94317",
      "url": "https://www.halooglasi.com/nekretnine/prodaja-stanova/moderan-stan-povrsine-59m-u-kompleksu-wellpor/5425646952514?kid=1",
      "naslov": "Naslov",
      "opis": "Prodaje se moderan stan površine 59m² u prestižnom kompleksu Wellport, faza IV. Stan je potpuno nov i neuseljavan, odlikuje se obiljem prirodnog svetla i p",
      "zgrada": "Wellport",
      "struktura": "ostalo",
      "cena": 100000.0,
      "m2": 59.0,
      "cena_m2": 1695,
      "agencija": null,
      "izvor": "halo"
    },
    {
      "id": "d82eaccc0454",
      "url": "https://www.halooglasi.com/nekretnine/prodaja-stanova/novi-beograd-west-65---tadije-sondermajera/5425644792193?kid=1",
      "naslov": "Naslov",
      "opis": "Novi Beograd, Blok 65 (West 65) - Tadije Sondermajera 5.0, 140m2 (terasa 16m2), 19/22, CG, tri lifta, telefon, interfon, parking, garaža U ponudi luksuzan,",
      "zgrada": "West 65",
      "struktura": "5.0",
      "cena": 100000.0,
      "m2": 140.0,
      "cena_m2": 714,
      "agencija": null,
      "izvor": "halo"
    },
    {
      "id": "2cb249633844",
      "url": "https://www.halooglasi.com/nekretnine/prodaja-stanova/tower-west-65---apsulutni-luksuz-u-kuli-west/5425646199301?kid=1",
      "naslov": "Naslov",
      "opis": "West Kula, Beograd | Simbol savremene arhitekture i života | Oaza na 60 m² Prodaje se kompletno opremljen, dizajnerski dvosoban stan površine 60 m² u najvi",
      "zgrada": "West 65 Kula",
      "struktura": "2.0",
      "cena": 100000.0,
      "m2": 60.0,
      "cena_m2": 1667,
      "agencija": null,
      "izvor": "halo"
    },
    {
      "id": "cdf22d055688",
      "url": "https://www.halooglasi.com/nekretnine/prodaja-stanova/new-minel-lux-kompletno-opremljen-2-0-stan/5425647080280?kid=1",
      "naslov": "Naslov",
      "opis": "U okviru New Minel kompleksa, prodaje se nov, namešten, luksuzno opremljen, dvosoban stan. Stan je dizajniran sa posebnim akcentom na kvalitet, funkcionaln",
      "zgrada": "New Minel",
      "struktura": "2.0",
      "cena": 100000.0,
      "m2": null,
      "cena_m2": null,
      "agencija": null,
      "izvor": "halo"
    },
    {
      "id": "1687563b4899",
      "url": "https://www.halooglasi.com/nekretnine/prodaja-stanova/luksuzno-opremljen-3-0-82m2-lastavica/5425645492773?kid=1",
      "naslov": "Naslov",
      "opis": "Komforan trosoban stan, površine 82m2, luksuzno je opremljen (uloženo 40.000 eur u opremanje stana). Nalazi se na četvrtom spratu osmospratne novoizgrađene",
      "zgrada": "Lastavica",
      "struktura": "3.0",
      "cena": 100000.0,
      "m2": 82.0,
      "cena_m2": 1220,
      "agencija": null,
      "izvor": "halo"
    },
    {
      "id": "2bd0d9f203ce",
      "url": "https://www.halooglasi.com/nekretnine/prodaja-stanova/west-kula---eksluzivna-prodaja-3-0-stan-garaz/5425647060892?kid=1",
      "naslov": "Naslov",
      "opis": "- Uknjižen 1/1. - Bez tereta i zabeležbi. - Moguća kupovina na kredit. - Uknjižena površina 95 m2. . - Trosoban. - Dvostrano orijentisan (sever–istok). - S",
      "zgrada": "West 65 Kula",
      "struktura": "3.0",
      "cena": 100000.0,
      "m2": 95.0,
      "cena_m2": 1053,
      "agencija": null,
      "izvor": "halo"
    },
    {
      "id": "be23052b70c8",
      "url": "https://www.halooglasi.com/nekretnine/prodaja-stanova/3-0-lux-novogradnja-soul64---useljiv/5425646665296?kid=1",
      "naslov": "Naslov",
      "opis": "Uživajte u luksuzu modernog života u novom naselju Soul 64 na Novom Beogradu, svega 7 minuta od obale Save. Ovaj useljiv stan površine 74 m² nalazi se na 3",
      "zgrada": "Soul 64",
      "struktura": "3.0",
      "cena": 100000.0,
      "m2": 74.0,
      "cena_m2": 1351,
      "agencija": null,
      "izvor": "halo"
    },
    {
      "id": "fb31274e953f",
      "url": "https://www.halooglasi.com/nekretnine/prodaja-stanova/a-blok/5425647311347?kid=1",
      "naslov": "Naslov",
      "opis": "U ponudi je svetao i funkcionalan dvosoban stan površine 56 m² u kompleksu A Blok na Novom Beogradu, jednom od najtraženijih i najbolje uređenih naselja u ",
      "zgrada": "A Blok",
      "struktura": "2.0",
      "cena": 100000.0,
      "m2": 56.0,
      "cena_m2": 1786,
      "agencija": null,
      "izvor": "halo"
    },
    {
      "id": "3332229e0c3c",
      "url": "https://www.halooglasi.com/nekretnine/prodaja-stanova/prodaja-stana-blok-71-renoviran-namesten-80m2/5425647106987?kid=1",
      "naslov": "Naslov",
      "opis": "Kontakt: Srdjan 0694455667 Novi Beograd, Blok 71 - Dr Ivana Ribara 75m2, 6/7, CG, lift, interfon, javni parking. Prodajemo odličan, funkcionalan i svetao t",
      "zgrada": "A Blok",
      "struktura": "ostalo",
      "cena": 100000.0,
      "m2": 75.0,
      "cena_m2": 1333,
      "agencija": null,
      "izvor": "halo"
    },
    {
      "id": "72435f35e936",
      "url": "https://www.halooglasi.com/nekretnine/prodaja-stanova/u-kompleksu-west-65-id1287/5425647059220?kid=1",
      "naslov": "Naslov",
      "opis": "Odličan, moderan trosoban stan uknjižen na 83 m², u prestižnom kompleksu West 65 na Novom Beogradu, pozicioniran na 4. spratu od ukupno 7. Ova stambena jed",
      "zgrada": "West 65",
      "struktura": "3.0",
      "cena": 100000.0,
      "m2": 83.0,
      "cena_m2": 1205,
      "agencija": null,
      "izvor": "halo"
    },
    {
      "id": "e1ff9be4a250",
      "url": "https://www.halooglasi.com/nekretnine/prodaja-stanova/lux-4-0-namesten-stan-od-112m2-new-minel/5425647050937?kid=1",
      "naslov": "Naslov",
      "opis": "Odličan četvosoban stan površine 112m2 u komleksu New Minel na Novom Beogradu, blok 65 na 2. spratu. Dnevni boravak, izdvojena kuhinja sa trpezarijom, tri ",
      "zgrada": "New Minel",
      "struktura": "4.0",
      "cena": 100000.0,
      "m2": 112.0,
      "cena_m2": 893,
      "agencija": null,
      "izvor": "halo"
    },
    {
      "id": "c02b778688f2",
      "url": "https://www.halooglasi.com/nekretnine/prodaja-stanova/bel-mondo-lux-novogradnja-id15494/5425647299459?kid=1",
      "naslov": "Naslov",
      "opis": "Na prodaju luksuzan trosoban stan u ekskluzivnom novoizgradjenom kompleksu Bel Mondo, Novi Beograd Stan površine 170 m2 (100 m2 stambenog prostora + 70 m2 ",
      "zgrada": "Bel Mondo",
      "struktura": "3.0",
      "cena": 100000.0,
      "m2": 170.0,
      "cena_m2": 588,
      "agencija": null,
      "izvor": "halo"
    },
    {
      "id": "ac48e3c4b942",
      "url": "https://www.halooglasi.com/nekretnine/prodaja-stanova/blok-62-47m2-basta-odlican/5425647294673?kid=1",
      "naslov": "Naslov",
      "opis": "U prilici smo da Vam ponudimo stan grejne povrsine 47 m2 plus terasa/bašta oko 30 m2 u stambenoj zgradi. Stan je sređen 1.5 u funkciji 2.5 Sastoji se od ma",
      "zgrada": "A Blok",
      "struktura": "1.5",
      "cena": 100000.0,
      "m2": 47.0,
      "cena_m2": 2128,
      "agencija": null,
      "izvor": "halo"
    },
    {
      "id": "86fb55b63e3c",
      "url": "https://www.halooglasi.com/nekretnine/prodaja-stanova/novi-beograd-west-65-trosoban-stan-100-m2/5425646885634?kid=1",
      "naslov": "Naslov",
      "opis": "Omladinskih brigada, West 65, trosoban, 100 m2, terasa, 3/6, uknjižen. U prilici smo da vam ponudimo izuzetan 3.0 stan na odličnoj lokaciji, sa dobrom infr",
      "zgrada": "West 65",
      "struktura": "3.0",
      "cena": 100000.0,
      "m2": 100.0,
      "cena_m2": 1000,
      "agencija": null,
      "izvor": "halo"
    },
    {
      "id": "c36682d58ef2",
      "url": "https://www.halooglasi.com/nekretnine/prodaja-stanova/west-65-kula-124m2-lux-cetvorosoban-stan/5425647292977?kid=1",
      "naslov": "Naslov",
      "opis": "Ekskluzivna ponuda, samo u našoj ponudi izuzetan četvorosoban stan u okviru kompleksa WEST 65, Novi Beograd. Kula West 65 predstavlja jedan od simbola grad",
      "zgrada": "West 65 Kula",
      "struktura": "4.0",
      "cena": 100000.0,
      "m2": null,
      "cena_m2": null,
      "agencija": null,
      "izvor": "halo"
    },
    {
      "id": "b3749f55cf8d",
      "url": "https://www.halooglasi.com/nekretnine/prodaja-stanova/lux-4-0-stan-od-113-18m2-the-one/5425646912666?kid=1",
      "naslov": "Naslov",
      "opis": "Odličan četvorosoban stan površine 113,18m2 u stambeno-poslovnom kompleksu The One na 5. spratu u ulici Omladinskih brigada. Sastoji se od dnevnog boravk",
      "zgrada": "The One",
      "struktura": "4.0",
      "cena": 100000.0,
      "m2": 18.0,
      "cena_m2": 5556,
      "agencija": null,
      "izvor": "halo"
    },
    {
      "id": "00835427e01d",
      "url": "https://www.halooglasi.com/nekretnine/prodaja-stanova/soul-64-53m-dvosoban/5425647194251",
      "naslov": "Naslov",
      "opis": "Prodaje se dvosoban stan u modernom stambenom kompleksu Soul64 na Novom Beogradu, površine 53m², smešten na VII od IX spratova. Južna orijentacija i visina",
      "zgrada": "Soul 64",
      "struktura": "2.0",
      "cena": 100000.0,
      "m2": 53.0,
      "cena_m2": 1887,
      "agencija": null,
      "izvor": "halo"
    },
    {
      "id": "07d06f4675fc",
      "url": "https://www.halooglasi.com/nekretnine/prodaja-stanova/odlican-3-0-stan-od-83-76m2-sakura-park/5425646905925?kid=1",
      "naslov": "Naslov",
      "opis": "Odličan trosoban stan površine 83,76m2 u novoizgrađenom kompleksu Sakura Park na 9. spratu. Preko puta naselja Belville i TC Delta City u bloku 58. Dnevni ",
      "zgrada": "Belvil",
      "struktura": "3.0",
      "cena": 100000.0,
      "m2": 76.0,
      "cena_m2": 1316,
      "agencija": null,
      "izvor": "halo"
    },
    {
      "id": "5c1fc181d900",
      "url": "https://www.halooglasi.com/nekretnine/prodaja-stanova/2-0-stan-u-west-kuli---najbolja-strana/5425645568593?kid=1",
      "naslov": "Naslov",
      "opis": "U ponudi je odličan stan u kuli West 65. Stan se nalazi na 14 spratu kule i ima prelep panoramski pogled. Stan je full smart home, ima 59m2 i sastoji se od",
      "zgrada": "West 65",
      "struktura": "2.0",
      "cena": 100000.0,
      "m2": 59.0,
      "cena_m2": 1695,
      "agencija": null,
      "izvor": "halo"
    },
    {
      "id": "3f9b26e03ea4",
      "url": "https://www.halooglasi.com/nekretnine/prodaja-stanova/pupinova-palata-98-29m2-id1836/5425647000047?kid=1",
      "naslov": "Naslov",
      "opis": "NAJATRAKTIVNIJA lokacija Novog Beograda, dobija velelepnu gradjevinu, jedinstvenu i nadaleko poznatu Pupinovu Palatu Jedan od najluksuzniijih objekata pres",
      "zgrada": "Pupinova palata",
      "struktura": "ostalo",
      "cena": 100000.0,
      "m2": null,
      "cena_m2": null,
      "agencija": null,
      "izvor": "halo"
    },
    {
      "id": "106ac5e97f07",
      "url": "https://www.halooglasi.com/nekretnine/prodaja-stanova/soul---premium---juzna-orijentacija/5425647030889?kid=1",
      "naslov": "Naslov",
      "opis": "SOUL Premium | 75m² | Južna orijentacija | Useljivo odmah U ponudi je luksuzan stan u prestižnoj SOUL premium zgradi, projektovan prema najvišim standardim",
      "zgrada": "Soul 64",
      "struktura": "ostalo",
      "cena": 100000.0,
      "m2": 75.0,
      "cena_m2": 1333,
      "agencija": null,
      "izvor": "halo"
    },
    {
      "id": "f8a02d730e17",
      "url": "https://www.halooglasi.com/nekretnine/prodaja-stanova/djordja-stanojevica-blok-65-novi-beograd-id79/5425645787848?kid=1",
      "naslov": "Naslov",
      "opis": "Luksuzan penthaus od 134m² u kompleksu Airport Garden – Novi Beograd Predstavljamo vam izuzetno komforan i luksuzan penthaus površine 134m², smešten u pres",
      "zgrada": "Airport Garden",
      "struktura": "ostalo",
      "cena": 100000.0,
      "m2": 134.0,
      "cena_m2": 746,
      "agencija": null,
      "izvor": "halo"
    },
    {
      "id": "8e4efa9ca1df",
      "url": "https://www.halooglasi.com/nekretnine/prodaja-stanova/soul-premium-one-bedroom-garaza-i-ostava-u-ce/5425647026899?kid=1",
      "naslov": "Naslov",
      "opis": "SOUL – Premium one bedroom | 55,67 m² | Garaža + ostava uključeni U ponudi je izuzetno svetao i funkcionalan stan u prestižnom kompleksu Soul, na 6. spratu",
      "zgrada": "Soul 64",
      "struktura": "ostalo",
      "cena": 100000.0,
      "m2": 67.0,
      "cena_m2": 1493,
      "agencija": null,
      "izvor": "halo"
    },
    {
      "id": "e7758761dfe3",
      "url": "https://www.halooglasi.com/nekretnine/prodaja-stanova/2-0-stan-54-kvm-soul-64-nbg/5425646943167?kid=1",
      "naslov": "Naslov",
      "opis": "Stan u luksuznom kompleksu Soul 64. Stan se nalazi na 4.spratu,B lamele,ukupne povrsine 54 m2. Uz stan se prodaje i garazno mesto na nivou -1, po ceni od 3",
      "zgrada": "Soul 64",
      "struktura": "2.0",
      "cena": 100000.0,
      "m2": 54.0,
      "cena_m2": 1852,
      "agencija": null,
      "izvor": "halo"
    },
    {
      "id": "2dd55665f511",
      "url": "https://www.halooglasi.com/nekretnine/prodaja-stanova/dvosoban-stan-airport-garden-novi-beograd/5425646890592?kid=1",
      "naslov": "Naslov",
      "opis": "Dvosoban stan, Airport Garden, Novi Beograd U novom i modernom kompleksu Airport Garden prodaje se komforan dvosoban stan od 58m2 na petom spratu – odličan",
      "zgrada": "Airport Garden",
      "struktura": "2.0",
      "cena": 100000.0,
      "m2": 58.0,
      "cena_m2": 1724,
      "agencija": null,
      "izvor": "halo"
    },
    {
      "id": "8bce1214d7bb",
      "url": "https://www.halooglasi.com/nekretnine/prodaja-stanova/west-65-kula/5425647269021?kid=1",
      "naslov": "Naslov",
      "opis": "Cena 399000 eura, ulica Omladinskih brigada West 65 Kula, 62m2, nov, lux, 2.0, sa garaznim mestom i panoramskim pogledom Lux, moderan, uknjizen 62m2, dvoso",
      "zgrada": "West 65 Kula",
      "struktura": "2.0",
      "cena": 100000.0,
      "m2": 62.0,
      "cena_m2": 1613,
      "agencija": null,
      "izvor": "halo"
    },
    {
      "id": "ae39dd50e54f",
      "url": "https://www.halooglasi.com/nekretnine/prodaja-stanova/novi-beograd-blok-67-belville-djordja-stanoje/5425647268897?kid=1",
      "naslov": "Naslov",
      "opis": "Novi Beograd, Blok 67 (Belville) - Đorđa Stanojevića 1.5, 41m2 (lođa 4m2), 4/13, CG, dva lifta, telefon, interfon, parking U ponudi očuvan izvorno jednosob",
      "zgrada": "Belvil",
      "struktura": "1.5",
      "cena": 100000.0,
      "m2": 41.0,
      "cena_m2": 2439,
      "agencija": null,
      "izvor": "halo"
    },
    {
      "id": "33b0135d7745",
      "url": "https://www.halooglasi.com/nekretnine/prodaja-stanova/kula-west-65-lux-2-0-namesten-stan-sa-garazom/5425645804749?kid=1",
      "naslov": "Naslov",
      "opis": "Novi Beograd, Blok 65 - Omladinskih brigada 2.0, 60m2, CG, 14/30, CG, garaža, interfon, telefon, klima, video nadzor. Izuzetno luksuzan stan u West kuli u ",
      "zgrada": "West 65",
      "struktura": "2.0",
      "cena": 100000.0,
      "m2": 60.0,
      "cena_m2": 1667,
      "agencija": null,
      "izvor": "halo"
    },
    {
      "id": "8d8a36da153d",
      "url": "https://www.halooglasi.com/nekretnine/prodaja-stanova/west-65-kula-70-m2-lux-garaza-zakupac-pogled/5425646538678?kid=1",
      "naslov": "Naslov",
      "opis": "Lux, moderan 69m2 stan, panoramskog pogleda,svetao, komletno opremljen kvalitetnim nameštajem, tehnikom i uređajima. U stanu je zakupac, koji želi da nasta",
      "zgrada": "West 65 Kula",
      "struktura": "ostalo",
      "cena": 100000.0,
      "m2": 69.0,
      "cena_m2": 1449,
      "agencija": null,
      "izvor": "halo"
    },
    {
      "id": "4f81efca18ad",
      "url": "https://www.halooglasi.com/nekretnine/prodaja-stanova/jedinstev-i-luksuzan-stan-u-kuli-west-65/5425646031260?kid=1",
      "naslov": "Naslov",
      "opis": "Jedinstven i luksuzan stan površine 123m2 na 4 spratu . Stan se sastoji od ulaznog hodnika , dve spavaće sobe koje imaju svoj garderober i kupatila , kuhin",
      "zgrada": "West 65",
      "struktura": "ostalo",
      "cena": 100000.0,
      "m2": 123.0,
      "cena_m2": 813,
      "agencija": null,
      "izvor": "halo"
    },
    {
      "id": "dbada1990b14",
      "url": "https://www.halooglasi.com/nekretnine/prodaja-stanova/novi-beograd-blok-60---tosin-bunar---new-mine/5425644804342?kid=1",
      "naslov": "Naslov",
      "opis": "Novi Beograd, Blok 60 - Tošin bunar - New Minel 4.0, 84m2, 12/22, CG, lift, klima, telefon, interfon, video nadzor, garaža Četvorosoban luksuzan stan u nov",
      "zgrada": "New Minel",
      "struktura": "4.0",
      "cena": 100000.0,
      "m2": 84.0,
      "cena_m2": 1190,
      "agencija": null,
      "izvor": "halo"
    },
    {
      "id": "32d23e27029c",
      "url": "https://www.halooglasi.com/nekretnine/prodaja-stanova/blok-45-blizina-reke-id1466411/5425646997443?kid=1",
      "naslov": "Naslov",
      "opis": "Uknjižen, 3s, 69 m2, I/II, CG, terasa, ostava. Komforan dvoiposoban stan na odličnoj lokaciji, u neposrednoj blizini Savskog keja, osnovne škole, doma zdra",
      "zgrada": "A Blok",
      "struktura": "2.5",
      "cena": 100000.0,
      "m2": 69.0,
      "cena_m2": 1449,
      "agencija": null,
      "izvor": "halo"
    },
    {
      "id": "dfc8379c6905",
      "url": "https://www.halooglasi.com/nekretnine/prodaja-stanova/fantasticna-novogradnja-tosin-bunar-savada-id/5425646805684?kid=1",
      "naslov": "Naslov",
      "opis": "Prodajemo izuzetan trosoban stan površine 91,87 m², koji se nalazi na 4. spratu u prestižnom stambenom kompleksu Savada 3, u Bloku 65 – savršenom mestu za ",
      "zgrada": "Savada",
      "struktura": "3.0",
      "cena": 100000.0,
      "m2": 87.0,
      "cena_m2": 1149,
      "agencija": null,
      "izvor": "halo"
    },
    {
      "id": "7e5199420215",
      "url": "https://www.halooglasi.com/nekretnine/prodaja-stanova/wellport-78m2-3-0-id8968/5425646723664?kid=1",
      "naslov": "Naslov",
      "opis": "Na prodaju moderan trosoban stan u prestižnom stambenom kompleksu Wellport, površine 78 m², projektovan po savremenom konceptu stanovanja sa naglaskom na k",
      "zgrada": "Wellport",
      "struktura": "3.0",
      "cena": 100000.0,
      "m2": 78.0,
      "cena_m2": 1282,
      "agencija": null,
      "izvor": "halo"
    }
  ]
}