{
  "date": "2026-07-12",
  "mode": "prodaja",
  "source": "nrs",
  "total_raw": 72,
  "total_unique": 59,
  "diff_new": [
    "154569db4319",
    "47a14f9b2b83",
    "b06589d80c7e",
    "fb70edf1bcc8"
  ],
  "diff_removed": [
    "5ee7b78e1d02",
    "3d6f70fef185",
    "920a1e100df4",
    "975f123e55e8"
  ],
  "listings": [
    {
      "id": "2ff2137db06a",
      "url": "https://www.nekretnine.rs/oglasi/1015817/",
      "naslov": "Dvosobni stan Ulica Omladinskih brigada, Belvil, Beograd",
      "opis": "Soul 64 Novo, 2.0 na veoma traženoj lokaciji bez buke, u kvalitetnoj zgradi sa odličnom odličnom izolacijom ,odlično saobraćajno povezan, brz pristup na velike bulevare, mostove,aerodrum 15",
      "zgrada": "Belvil",
      "struktura": "2.0",
      "cena": 261250.0,
      "m2": 55.0,
      "cena_m2": 4750,
      "agencija": "DANOS AND ASSOCIATES",
      "agencija_url": "https://www.nekretnine.rs/agencije-za-nekretnine/1135/",
      "izvor": "nrs"
    },
    {
      "id": "cb4720c058ab",
      "url": "https://www.nekretnine.rs/oglasi/1193411/",
      "naslov": "Trosobni stan Ulica Omladinskih brigada, Stari Aerodrom, Beograd",
      "opis": "Bel Mondo je novi rezidencijalni kompleks u centralnom delu Novog Beograda, gradnja je upravo završena, a stan je useljiv u kratkom roku. Kompleks nudi 24-časovnu recepciju i obezbeđenje,",
      "zgrada": "Bel Mondo",
      "struktura": "3.0",
      "cena": 870000.0,
      "m2": 170.0,
      "cena_m2": 5118,
      "agencija": "RElife NEKRETNINE",
      "agencija_url": "https://www.nekretnine.rs/agencije-za-nekretnine/749/",
      "izvor": "nrs"
    },
    {
      "id": "84c97c184db4",
      "url": "https://www.nekretnine.rs/oglasi/1051697/",
      "naslov": "Dvosobni stan odlično stanje, četvrti sprat, Mladost, Beograd",
      "opis": "U prilici smo da Vam ponudimo na prodaju odmah useljiv dvosoban stan u novogradnji na atraktivnoj lokaciji Novog Beograda, u kompleksu Soul 64, u zgradi E.\n\nStan se nalazi na 4. spratu, ima ukupnu",
      "zgrada": "Soul 64",
      "struktura": "2.0",
      "cena": 275000.0,
      "m2": 54.0,
      "cena_m2": 5093,
      "agencija": "LATERNA NEKRETNINE",
      "agencija_url": "https://www.nekretnine.rs/agencije-za-nekretnine/559/",
      "izvor": "nrs"
    },
    {
      "id": "091300bc7638",
      "url": "https://www.nekretnine.rs/oglasi/1133611/",
      "naslov": "Stan Ulica Omladinskih brigada 84g, Stari Aerodrom, Beograd",
      "opis": "BEL MONDO je novi stambeno-poslovni projekat sa jedinstvenom vizijom bezbrižne, ušuškane oaze u urbanom okruženju.\n\nBEL MONDO predstavlja sklad dinamične zajednice, bogate raznovrsnim",
      "zgrada": "Bel Mondo",
      "struktura": "5.0",
      "cena": null,
      "m2": 250.0,
      "cena_m2": null,
      "agencija": "Bel Mondo",
      "agencija_url": "https://www.nekretnine.rs/agencije-za-nekretnine/4845/",
      "izvor": "nrs"
    },
    {
      "id": "a644ae99a551",
      "url": "https://www.nekretnine.rs/oglasi/1133527/",
      "naslov": "Stan Ulica Omladinskih brigada 84g, Stari Aerodrom, Beograd",
      "opis": "BEL MONDO predstavlja sklad dinamične zajednice, bogate raznovrsnim sadržajima i prijatnim ambijentom koji pruža osećaj privatnosti i udobnosti. Smešten u centralnom delu Novog Beograda, sa",
      "zgrada": "Bel Mondo",
      "struktura": "ostalo",
      "cena": null,
      "m2": 73.0,
      "cena_m2": null,
      "agencija": "Bel Mondo",
      "agencija_url": "https://www.nekretnine.rs/agencije-za-nekretnine/4845/",
      "izvor": "nrs"
    },
    {
      "id": "17ec9daeb4da",
      "url": "https://www.nekretnine.rs/oglasi/1191863/",
      "naslov": "Stan Ulica Omladinskih brigada, Stari Aerodrom, Beograd",
      "opis": "Sofisticiran i do detalja opremljen stan, kao stvoren za najistančanije ukuse, nalazi se u najluksuznijem kompleksu na Novom Beogradu – West 65. Topli tonovi pružaju ovom prostranom stanu posebnu",
      "zgrada": "West 65",
      "struktura": "5.0",
      "cena": null,
      "m2": 444.0,
      "cena_m2": null,
      "agencija": "KADENA SOTHEBY'S INTERNATIONAL REALTY",
      "agencija_url": "https://www.nekretnine.rs/agencije-za-nekretnine/345/",
      "izvor": "nrs"
    },
    {
      "id": "4e4bdfc60138",
      "url": "https://www.nekretnine.rs/oglasi/1133567/",
      "naslov": "Stan Ulica Omladinskih brigada 84g, Stari Aerodrom, Beograd",
      "opis": "BEL MONDO predstavlja sklad dinamične zajednice, bogate raznovrsnim sadržajima i prijatnim ambijentom koji pruža osećaj privatnosti i udobnosti. Smešten u centralnom delu Novog Beograda, sa",
      "zgrada": "Bel Mondo",
      "struktura": "5.0",
      "cena": null,
      "m2": 252.0,
      "cena_m2": null,
      "agencija": "Bel Mondo",
      "agencija_url": "https://www.nekretnine.rs/agencije-za-nekretnine/4845/",
      "izvor": "nrs"
    },
    {
      "id": "0e4eb8bc3489",
      "url": "https://www.nekretnine.rs/oglasi/1133575/",
      "naslov": "Stan Ulica Omladinskih brigada 84g, Stari Aerodrom, Beograd",
      "opis": "BEL MONDO predstavlja sklad dinamične zajednice, bogate raznovrsnim sadržajima i prijatnim ambijentom koji pruža osećaj privatnosti i udobnosti. Smešten u centralnom delu Novog Beograda, sa",
      "zgrada": "Bel Mondo",
      "struktura": "5.0",
      "cena": null,
      "m2": 200.0,
      "cena_m2": null,
      "agencija": "Bel Mondo",
      "agencija_url": "https://www.nekretnine.rs/agencije-za-nekretnine/4845/",
      "izvor": "nrs"
    },
    {
      "id": "f640ea5eaf1f",
      "url": "https://www.nekretnine.rs/oglasi/1133601/",
      "naslov": "Stan Ulica Omladinskih brigada 84g, Stari Aerodrom, Beograd",
      "opis": "BEL MONDO predstavlja sklad dinamične zajednice, bogate raznovrsnim sadržajima i prijatnim ambijentom koji pruža osećaj privatnosti i udobnosti. Smešten u centralnom delu Novog Beograda, sa",
      "zgrada": "Bel Mondo",
      "struktura": "5.0",
      "cena": null,
      "m2": 217.0,
      "cena_m2": null,
      "agencija": "Bel Mondo",
      "agencija_url": "https://www.nekretnine.rs/agencije-za-nekretnine/4845/",
      "izvor": "nrs"
    },
    {
      "id": "78044578ffb1",
      "url": "https://www.nekretnine.rs/oglasi/1133617/",
      "naslov": "Penthaus Ulica Omladinskih brigada 84g, Stari Aerodrom, Beograd",
      "opis": "BEL MONDO predstavlja sklad dinamične zajednice, bogate raznovrsnim sadržajima i prijatnim ambijentom koji pruža osećaj privatnosti i udobnosti. Smešten u centralnom delu Novog Beograda, sa",
      "zgrada": "Bel Mondo",
      "struktura": "5.0",
      "cena": null,
      "m2": 386.0,
      "cena_m2": null,
      "agencija": "Bel Mondo",
      "agencija_url": "https://www.nekretnine.rs/agencije-za-nekretnine/4845/",
      "izvor": "nrs"
    },
    {
      "id": "92a7d6bc9ddf",
      "url": "https://www.nekretnine.rs/oglasi/1211405/",
      "naslov": "Stan Ulica Djordja Stanojevica 35, Mladost, Beograd",
      "opis": "Airport Garden | Novogradnja | 32 m² | II sprat\n\nProdaje se potpuno nov, neuseljavan jednosoban stan površine 32 m² u premium kompleksu Airport Garden, lamela B, na Novom Beogradu.\n\nNalazi se na",
      "zgrada": "Airport Garden",
      "struktura": "garsonjera",
      "cena": 157900.0,
      "m2": 32.0,
      "cena_m2": 4934,
      "agencija": null,
      "agencija_url": null,
      "izvor": "nrs"
    },
    {
      "id": "04e34e794360",
      "url": "https://www.nekretnine.rs/oglasi/74973/",
      "naslov": "Četvorosobni stan Tošin bunar, Stari Aerodrom, Beograd",
      "opis": "Pupinova palata na Novom Beogradu oslikava idealan spoj materijalizacije premium kvaliteta i najsavremenije tehnologije. Atraktivan izgled i moderan dizajn ovog objekta izuzetno doprinose",
      "zgrada": "Pupinova palata",
      "struktura": "4.0",
      "cena": 391620.0,
      "m2": 107.0,
      "cena_m2": 3660,
      "agencija": "FENIKS SISTEM",
      "agencija_url": "https://www.nekretnine.rs/agencije-za-nekretnine/227/",
      "izvor": "nrs"
    },
    {
      "id": "44f0452a3287",
      "url": "https://www.nekretnine.rs/oglasi/73123/",
      "naslov": "Četvorosobni stan Tošin bunar, Stari Aerodrom, Beograd",
      "opis": "Pupinova palata na Novom Beogradu oslikava idealan spoj materijalizacije premium kvaliteta i najsavremenije tehnologije. Atraktivan izgled i moderan dizajn ovog objekta izuzetno doprinose",
      "zgrada": "Pupinova palata",
      "struktura": "4.0",
      "cena": 341066.0,
      "m2": 98.0,
      "cena_m2": 3480,
      "agencija": "FENIKS SISTEM",
      "agencija_url": "https://www.nekretnine.rs/agencije-za-nekretnine/227/",
      "izvor": "nrs"
    },
    {
      "id": "9fbc9a481a2f",
      "url": "https://www.nekretnine.rs/oglasi/1019471/",
      "naslov": "Dvosobni stan Jurija Gagarina, Savski kej, Beograd",
      "opis": "2.0, 62m (lođa 6,30m), 2/10, lift, CG, interfon, internet, klima, KTV, video-nadzor  Savremeni stambeni kompleks Lastavice nalazi se u ulici Jurija Gagarina i važi za jednu od najtraženijih i",
      "zgrada": "Lastavica",
      "struktura": "2.0",
      "cena": 309000.0,
      "m2": 62.0,
      "cena_m2": 4984,
      "agencija": "GALERIJA NEKRETNINE",
      "agencija_url": "https://www.nekretnine.rs/agencije-za-nekretnine/609/",
      "izvor": "nrs"
    },
    {
      "id": "c008dd490190",
      "url": "https://www.nekretnine.rs/oglasi/1039677/",
      "naslov": "Četvorosobni stan Džona Kenedija, Donji Grad, Beograd",
      "opis": "Novi Beograd, Blok 9a - Džona Kenedija  4.0, 167m2 (terasa 8m2), 10/10, podno grejanje, lift, telefon, interfon, garaža  U okviru prestižnog kompleksa Kennedy Residences, na jednoj od",
      "zgrada": "Kennedy Residence",
      "struktura": "4.0",
      "cena": 949999.0,
      "m2": 167.0,
      "cena_m2": 5689,
      "agencija": "MOJ KVADRAT",
      "agencija_url": "https://www.nekretnine.rs/agencije-za-nekretnine/1049/",
      "izvor": "nrs"
    },
    {
      "id": "2da16b00ad01",
      "url": "https://www.nekretnine.rs/oglasi/72129/",
      "naslov": "Trosobni stan Jurija Gagarina, Savski kej, Beograd",
      "opis": "U zgradi \"Lastavica\" preko puta Delta City-ja, odličanapartman na prvom spratu. Sve je novo i odlično izvedeno. U zgradi ima lokala, kafića.\nPoželjni su keš kupci.\nKupac plaća agencijsku",
      "zgrada": "Lastavica",
      "struktura": "3.0",
      "cena": 315000.0,
      "m2": 82.0,
      "cena_m2": 3841,
      "agencija": "FENIKS SISTEM",
      "agencija_url": "https://www.nekretnine.rs/agencije-za-nekretnine/227/",
      "izvor": "nrs"
    },
    {
      "id": "5800661f641d",
      "url": "https://www.nekretnine.rs/oglasi/1262911/",
      "naslov": "Trosobni stan Uroša Martinovića, Belvil, Beograd",
      "opis": "Stan se nalazi na jednoj od prestižnih lokacija Novog Beograda u Savadi, povučen od ulice, ušuškan u parkovskom okruženju, u zgradi koja je uredna, besprekorno čista.\nU neposrednoj blizini su",
      "zgrada": "Belvil",
      "struktura": "3.0",
      "cena": 360000.0,
      "m2": 81.0,
      "cena_m2": 4444,
      "agencija": "BEOSTIL NEKRETNINE-STILIKO",
      "agencija_url": "https://www.nekretnine.rs/agencije-za-nekretnine/955/",
      "izvor": "nrs"
    },
    {
      "id": "e78fdb3ffe3d",
      "url": "https://www.nekretnine.rs/oglasi/1255967/",
      "naslov": "Trosobni stan Jurija Gagarina, Mladost, Beograd",
      "opis": "U luksuznom objektu Sakura park nalazi se ovaj trosoban stan od 84m2. Stan nije nikada useljavan. Prostorije: predsoblje, dve spavaće sobe, dnevni boravak sa kuhinjom, dva kompletna kupatila, lepa",
      "zgrada": "Sakura Park",
      "struktura": "3.0",
      "cena": 385000.0,
      "m2": 84.0,
      "cena_m2": 4583,
      "agencija": "ATAŠE NEKRETNINE",
      "agencija_url": "https://www.nekretnine.rs/agencije-za-nekretnine/783/",
      "izvor": "nrs"
    },
    {
      "id": "19e8979ac108",
      "url": "https://www.nekretnine.rs/oglasi/1255971/",
      "naslov": "Trosobni stan Jurija Gagarina, Mladost, Beograd",
      "opis": "U luksuznom objektu Sakura park nalazi se ovaj trosoban stan od 76m2. Stan nije nikada useljavan. Prostorije: predsoblje, dve spavaće sobe, dnevni boravak sa kuhinjom, dva mokra čvora, lepa velika",
      "zgrada": "Sakura Park",
      "struktura": "3.0",
      "cena": 350000.0,
      "m2": 76.0,
      "cena_m2": 4605,
      "agencija": "ATAŠE NEKRETNINE",
      "agencija_url": "https://www.nekretnine.rs/agencije-za-nekretnine/783/",
      "izvor": "nrs"
    },
    {
      "id": "95bcc2f2060e",
      "url": "https://www.nekretnine.rs/oglasi/1035411/",
      "naslov": "Trosobni stan u dobrom stanju, treći sprat, Savski kej, Beograd",
      "opis": "Na prodaju moderan trosoban stan na Novom Beogradu, u prestižnom kompleksu Sakura Park, jednom od najkvalitetnijih projekata novogradnje u ovom delu grada.  Stan se nalazi na jednoj od",
      "zgrada": "Sakura Park",
      "struktura": "3.0",
      "cena": 410000.0,
      "m2": 99.0,
      "cena_m2": 4141,
      "agencija": "KREDIUM",
      "agencija_url": "https://www.nekretnine.rs/agencije-za-nekretnine/383/",
      "izvor": "nrs"
    },
    {
      "id": "7906b34bf601",
      "url": "https://www.nekretnine.rs/oglasi/843473/",
      "naslov": "Trosobni stan Bulevar Crvene Armije, Belvil, Beograd",
      "opis": "Kvalitetna zgrada iz 2010-e godine sa 2 lifta. Prijatan i tih stan sa sa terasama za uživanje. Zapadne osunčane orjentacije (dnevna, trpezarija i kuhinja) i istočne (spavaće sobe). Kompletnu",
      "zgrada": "Belvil",
      "struktura": "3.0",
      "cena": 399000.0,
      "m2": 106.0,
      "cena_m2": 3764,
      "agencija": "ATAŠE NEKRETNINE",
      "agencija_url": "https://www.nekretnine.rs/agencije-za-nekretnine/783/",
      "izvor": "nrs"
    },
    {
      "id": "607d1c6f2acf",
      "url": "https://www.nekretnine.rs/oglasi/1055595/",
      "naslov": "Trosobni stan Omladinskih Brigada, Belvil, Beograd",
      "opis": "Omladinskih brigada, West 65, trosoban, 100 m2, terasa, 3/6, uknjižen.\n\nU prilici smo da vam ponudimo izuzetan 3.0 stan na odličnoj lokaciji, sa dobrom infrastrukturom i svim potrebnim sadržajima",
      "zgrada": "Belvil",
      "struktura": "3.0",
      "cena": 590000.0,
      "m2": 100.0,
      "cena_m2": 5900,
      "agencija": "ZIDART",
      "agencija_url": "https://www.nekretnine.rs/agencije-za-nekretnine/155/",
      "izvor": "nrs"
    },
    {
      "id": "0cb42a404f40",
      "url": "https://www.nekretnine.rs/oglasi/1039241/",
      "naslov": "Dvosobni stan Ulica Omladinskih brigada 100, Mladost, Beograd",
      "opis": "Soul 64 Novo, 2.0 na veoma traženoj lokaciji bez buke, u kvalitetnoj zgradi sa odličnom odličnom izolacijom ,odlično saobraćajno povezan, brz pristup na velike bulevare, mostove,aerodrum 15",
      "zgrada": "Soul 64",
      "struktura": "2.0",
      "cena": 261750.0,
      "m2": 56.0,
      "cena_m2": 4674,
      "agencija": "DANOS AND ASSOCIATES",
      "agencija_url": "https://www.nekretnine.rs/agencije-za-nekretnine/1135/",
      "izvor": "nrs"
    },
    {
      "id": "a1e1d35f4c5a",
      "url": "https://www.nekretnine.rs/oglasi/1004601/",
      "naslov": "Trosobni stan Omladinskih brigada, Bežanija, Beograd",
      "opis": "Prodaje se odličan trosoban stan u luksuznom stambenom kompleksu West 65, jednom od najtraženijih i najkvalitetnijih kompleksa na Novom Beogradu.&lt;/br&gt;\n\nStan je veoma funkcionalnog rasporeda i",
      "zgrada": "West 65",
      "struktura": "3.0",
      "cena": 450000.0,
      "m2": 90.0,
      "cena_m2": 5000,
      "agencija": "DIVIS NEKRETNINE",
      "agencija_url": "https://www.nekretnine.rs/agencije-za-nekretnine/561/",
      "izvor": "nrs"
    },
    {
      "id": "5d22ab35275c",
      "url": "https://www.nekretnine.rs/oglasi/1046271/",
      "naslov": "Četvorosobni stan Jurija Gagarina, Savski kej, Beograd",
      "opis": "Luksuzan četvorosoban stan idealne strukture i orijentacije, komforan i osunčan sa velikim staklenim povr&scaron;inama u novoizgrađenom kompleksu Lastavice na Novom Beogradu, preko puta TC Delta",
      "zgrada": "Lastavica",
      "struktura": "4.0",
      "cena": 380000.0,
      "m2": 83.0,
      "cena_m2": 4578,
      "agencija": "DIVIS NEKRETNINE",
      "agencija_url": "https://www.nekretnine.rs/agencije-za-nekretnine/561/",
      "izvor": "nrs"
    },
    {
      "id": "e49b7dd30ff4",
      "url": "https://www.nekretnine.rs/oglasi/1011227/",
      "naslov": "Dvosobni stan u dobrom stanju, peti sprat, Belvil, Beograd",
      "opis": "Dvosoban stan, Airport Garden, Novi Beograd  U novom i modernom kompleksu Airport Garden prodaje se komforan dvosoban stan od 58m2 na petom spratu  odličan izbor za savremen način života ili kao",
      "zgrada": "Airport Garden",
      "struktura": "2.0",
      "cena": 237800.0,
      "m2": 58.0,
      "cena_m2": 4100,
      "agencija": "ETAGI COM",
      "agencija_url": "https://www.nekretnine.rs/agencije-za-nekretnine/1095/",
      "izvor": "nrs"
    },
    {
      "id": "a90e9466809d",
      "url": "https://www.nekretnine.rs/oglasi/1007983/",
      "naslov": "Dvosobni stan Đorđa Stanojevića, Belvil, Beograd",
      "opis": "Na prodaju izuzetno kvalitetan i moderan stan u luksuznom kompleksu Airport Garden, u novoj zgradi završenoj krajem 2025. godine.\n\nStan se nalazi na 4. spratu od ukupno 10 spratova i pruža odličan",
      "zgrada": "Airport Garden",
      "struktura": "2.0",
      "cena": 259800.0,
      "m2": 60.0,
      "cena_m2": 4330,
      "agencija": "LUSSO NEKRETNINE",
      "agencija_url": "https://www.nekretnine.rs/agencije-za-nekretnine/281/",
      "izvor": "nrs"
    },
    {
      "id": "b96201f79cc8",
      "url": "https://www.nekretnine.rs/oglasi/1205207/",
      "naslov": "Dvosobni stan A blok, Belvil, Beograd",
      "opis": "U ponudi je svetao i funkcionalan dvosoban stan površine 56 m u kompleksu A Blok na Novom Beogradu, jednom od najtraženijih i najbolje uređenih naselja u gradu. Stan je uknjižen 1/1 i može biti",
      "zgrada": "A Blok",
      "struktura": "2.0",
      "cena": 280000.0,
      "m2": 56.0,
      "cena_m2": 5000,
      "agencija": "ECONOMIC NET SYSTEM",
      "agencija_url": "https://www.nekretnine.rs/agencije-za-nekretnine/1021/",
      "izvor": "nrs"
    },
    {
      "id": "62a6508f0295",
      "url": "https://www.nekretnine.rs/oglasi/1133587/",
      "naslov": "Stan Ulica Omladinskih brigada 84g, Stari Aerodrom, Beograd",
      "opis": "BEL MONDO predstavlja sklad dinamične zajednice, bogate raznovrsnim sadržajima i prijatnim ambijentom koji pruža osećaj privatnosti i udobnosti. Smešten u centralnom delu Novog Beograda, sa",
      "zgrada": "Bel Mondo",
      "struktura": "5.0",
      "cena": null,
      "m2": 212.0,
      "cena_m2": null,
      "agencija": "Bel Mondo",
      "agencija_url": "https://www.nekretnine.rs/agencije-za-nekretnine/4845/",
      "izvor": "nrs"
    },
    {
      "id": "2b80d2098fa6",
      "url": "https://www.nekretnine.rs/oglasi/1133565/",
      "naslov": "Stan Ulica Omladinskih brigada 84g, Stari Aerodrom, Beograd",
      "opis": "BEL MONDO predstavlja sklad dinamične zajednice, bogate raznovrsnim sadržajima i prijatnim ambijentom koji pruža osećaj privatnosti i udobnosti. Smešten u centralnom delu Novog Beograda, sa",
      "zgrada": "Bel Mondo",
      "struktura": "ostalo",
      "cena": null,
      "m2": 121.0,
      "cena_m2": null,
      "agencija": "Bel Mondo",
      "agencija_url": "https://www.nekretnine.rs/agencije-za-nekretnine/4845/",
      "izvor": "nrs"
    },
    {
      "id": "679997846b66",
      "url": "https://www.nekretnine.rs/oglasi/1133547/",
      "naslov": "Stan Ulica Omladinskih brigada 84g, Stari Aerodrom, Beograd",
      "opis": "BEL MONDO predstavlja sklad dinamične zajednice, bogate raznovrsnim sadržajima i prijatnim ambijentom koji pruža osećaj privatnosti i udobnosti. Smešten u centralnom delu Novog Beograda, sa",
      "zgrada": "Bel Mondo",
      "struktura": "5.0",
      "cena": null,
      "m2": 187.0,
      "cena_m2": null,
      "agencija": "Bel Mondo",
      "agencija_url": "https://www.nekretnine.rs/agencije-za-nekretnine/4845/",
      "izvor": "nrs"
    },
    {
      "id": "bb3f6d42d97d",
      "url": "https://www.nekretnine.rs/oglasi/1133533/",
      "naslov": "Stan Ulica Omladinskih brigada 84g, Stari Aerodrom, Beograd",
      "opis": "BEL MONDO predstavlja sklad dinamične zajednice, bogate raznovrsnim sadržajima i prijatnim ambijentom koji pruža osećaj privatnosti i udobnosti. Smešten u centralnom delu Novog Beograda, sa",
      "zgrada": "Bel Mondo",
      "struktura": "ostalo",
      "cena": null,
      "m2": 79.0,
      "cena_m2": null,
      "agencija": "Bel Mondo",
      "agencija_url": "https://www.nekretnine.rs/agencije-za-nekretnine/4845/",
      "izvor": "nrs"
    },
    {
      "id": "597286a26a61",
      "url": "https://www.nekretnine.rs/oglasi/1133573/",
      "naslov": "Stan Ulica Omladinskih brigada 84g, Stari Aerodrom, Beograd",
      "opis": "BEL MONDO predstavlja sklad dinamične zajednice, bogate raznovrsnim sadržajima i prijatnim ambijentom koji pruža osećaj privatnosti i udobnosti. Smešten u centralnom delu Novog Beograda, sa",
      "zgrada": "Bel Mondo",
      "struktura": "5.0",
      "cena": null,
      "m2": 218.0,
      "cena_m2": null,
      "agencija": "Bel Mondo",
      "agencija_url": "https://www.nekretnine.rs/agencije-za-nekretnine/4845/",
      "izvor": "nrs"
    },
    {
      "id": "cfbc851153af",
      "url": "https://www.nekretnine.rs/oglasi/1133561/",
      "naslov": "Stan Ulica Omladinskih brigada 84g, Stari Aerodrom, Beograd",
      "opis": "BEL MONDO predstavlja sklad dinamične zajednice, bogate raznovrsnim sadržajima i prijatnim ambijentom koji pruža osećaj privatnosti i udobnosti. Smešten u centralnom delu Novog Beograda, sa",
      "zgrada": "Bel Mondo",
      "struktura": "ostalo",
      "cena": null,
      "m2": 111.0,
      "cena_m2": null,
      "agencija": "Bel Mondo",
      "agencija_url": "https://www.nekretnine.rs/agencije-za-nekretnine/4845/",
      "izvor": "nrs"
    },
    {
      "id": "bfbfe68cc885",
      "url": "https://www.nekretnine.rs/oglasi/1133577/",
      "naslov": "Penthaus Ulica Omladinskih brigada 84g, Stari Aerodrom, Beograd",
      "opis": "BEL MONDO predstavlja sklad dinamične zajednice, bogate raznovrsnim sadržajima i prijatnim ambijentom koji pruža osećaj privatnosti i udobnosti. Smešten u centralnom delu Novog Beograda, sa",
      "zgrada": "Bel Mondo",
      "struktura": "5.0",
      "cena": null,
      "m2": 265.0,
      "cena_m2": null,
      "agencija": "Bel Mondo",
      "agencija_url": "https://www.nekretnine.rs/agencije-za-nekretnine/4845/",
      "izvor": "nrs"
    },
    {
      "id": "bdbf52a5b5b7",
      "url": "https://www.nekretnine.rs/oglasi/1133557/",
      "naslov": "Stan Ulica Omladinskih brigada 84g, Stari Aerodrom, Beograd",
      "opis": "BEL MONDO predstavlja sklad dinamične zajednice, bogate raznovrsnim sadržajima i prijatnim ambijentom koji pruža osećaj privatnosti i udobnosti. Smešten u centralnom delu Novog Beograda, sa",
      "zgrada": "Bel Mondo",
      "struktura": "ostalo",
      "cena": null,
      "m2": 123.0,
      "cena_m2": null,
      "agencija": "Bel Mondo",
      "agencija_url": "https://www.nekretnine.rs/agencije-za-nekretnine/4845/",
      "izvor": "nrs"
    },
    {
      "id": "b06589d80c7e",
      "url": "https://www.nekretnine.rs/oglasi/1272143/",
      "naslov": "Četvorosobni stan Tošin bunar, Mladost, Beograd",
      "opis": "U ponudi izuzetan troiposoban stan u stambenom naselju Savada 3. Veoma svetao, zapadno orijentisan. Funkcionalnog rasporeda. \n\nModeran koncept. \n\nDnevna soba sa kuhinjom i trpezarijom, dve velike",
      "zgrada": "Savada",
      "struktura": "4.0",
      "cena": 395000.0,
      "m2": 97.0,
      "cena_m2": 4072,
      "agencija": "MEGASTAN",
      "agencija_url": "https://www.nekretnine.rs/agencije-za-nekretnine/1015/",
      "izvor": "nrs"
    },
    {
      "id": "54817652d07b",
      "url": "https://www.nekretnine.rs/oglasi/1133523/",
      "naslov": "Stan Ulica Omladinskih brigada 84g, Stari Aerodrom, Beograd",
      "opis": "BEL MONDO predstavlja sklad dinamične zajednice, bogate raznovrsnim sadržajima i prijatnim ambijentom koji pruža osećaj privatnosti i udobnosti. Smešten u centralnom delu Novog Beograda, sa",
      "zgrada": "Bel Mondo",
      "struktura": "ostalo",
      "cena": null,
      "m2": 83.0,
      "cena_m2": null,
      "agencija": "Bel Mondo",
      "agencija_url": "https://www.nekretnine.rs/agencije-za-nekretnine/4845/",
      "izvor": "nrs"
    },
    {
      "id": "e216571d6eec",
      "url": "https://www.nekretnine.rs/oglasi/1133545/",
      "naslov": "Stan Ulica Omladinskih brigada 84g, Stari Aerodrom, Beograd",
      "opis": "BEL MONDO predstavlja sklad dinamične zajednice, bogate raznovrsnim sadržajima i prijatnim ambijentom koji pruža osećaj privatnosti i udobnosti. Smešten u centralnom delu Novog Beograda, sa",
      "zgrada": "Bel Mondo",
      "struktura": "5.0",
      "cena": null,
      "m2": 186.0,
      "cena_m2": null,
      "agencija": "Bel Mondo",
      "agencija_url": "https://www.nekretnine.rs/agencije-za-nekretnine/4845/",
      "izvor": "nrs"
    },
    {
      "id": "b7613fafbe6d",
      "url": "https://www.nekretnine.rs/oglasi/1269365/",
      "naslov": "Dvosobni stan Omladinskih brigada, Belvil, Beograd",
      "opis": "Prodaje se potpuno nov, odmah useljiv, dvosoban stan u kompleksu Soul 64.\n\nProstor je modernog koncepta, sa puno svetlosti, prozori su od poda do plafona.\nOdlična nekretnina kako za život, tako i",
      "zgrada": "Belvil",
      "struktura": "2.0",
      "cena": 263000.0,
      "m2": 56.0,
      "cena_m2": 4696,
      "agencija": "ART NEKRETNINE",
      "agencija_url": "https://www.nekretnine.rs/agencije-za-nekretnine/241/",
      "izvor": "nrs"
    },
    {
      "id": "fb70edf1bcc8",
      "url": "https://www.nekretnine.rs/oglasi/1271313/",
      "naslov": "Dvosobni stan Đorđa Stanojevića, Mladost, Beograd",
      "opis": "U prestižnom poslovno-stambenom kompleksu Airport Garden, na Novom Beogradu, nalazi se izuzetno funkcionalan i svetao dvosoban stan, smešten na prvom spratu moderne zgrade.\n\nStan je pažljivo",
      "zgrada": "Airport Garden",
      "struktura": "2.0",
      "cena": 256750.0,
      "m2": 65.0,
      "cena_m2": 3950,
      "agencija": "PROPERTY BROKER",
      "agencija_url": "https://www.nekretnine.rs/agencije-za-nekretnine/717/",
      "izvor": "nrs"
    },
    {
      "id": "363c5d6679e6",
      "url": "https://www.nekretnine.rs/oglasi/1156915/",
      "naslov": "Jednosoban stan Đorđa Stanojevića, Belvil, Beograd",
      "opis": "Prodajemo atraktivan studio na jednoj od najperspektivnijih lokacija na Novom Beogradu. Blizina svih sadržaja potrebnih za udoban život. Uređene zelene porvšine. Kvalitetna gradnja, moderna",
      "zgrada": "Belvil",
      "struktura": "garsonjera",
      "cena": 157900.0,
      "m2": 32.0,
      "cena_m2": 4934,
      "agencija": "BELI GRAD NEKRETNINE",
      "agencija_url": "https://www.nekretnine.rs/agencije-za-nekretnine/341/",
      "izvor": "nrs"
    },
    {
      "id": "75086dc562ac",
      "url": "https://www.nekretnine.rs/oglasi/1259063/",
      "naslov": "Trosobni stan Jurija Gagarina, Savski kej, Beograd",
      "opis": "Lux stan u prestižnom kompleksu Lastavica nudi jedinstvenu kombinaciju luksuza, sigurnosti i prirodne lepote. Smešten u blizini reke, ovaj stan pruža miran i opuštajući ambijent, idealan za sve",
      "zgrada": "Lastavica",
      "struktura": "3.0",
      "cena": 379000.0,
      "m2": 82.0,
      "cena_m2": 4622,
      "agencija": "EUROPOLIS REAL ESTATE",
      "agencija_url": "https://www.nekretnine.rs/agencije-za-nekretnine/579/",
      "izvor": "nrs"
    },
    {
      "id": "98e82a6387cd",
      "url": "https://www.nekretnine.rs/oglasi/1017105/",
      "naslov": "Dvosobni stan novo, sedmi sprat, Mladost, Beograd",
      "opis": "U luksuznom  novom naselju Soul 64 na Novom Beogradu, prodaje se stan dvosobne strukture, dvorišno  orijentisan, pozicioniran na sedmom spratu. Stan je površine 53m2 i sastoji se od ulaznog",
      "zgrada": "Soul 64",
      "struktura": "2.0",
      "cena": 280000.0,
      "m2": 53.0,
      "cena_m2": 5283,
      "agencija": "BENEFIT NEKRETNINE",
      "agencija_url": "https://www.nekretnine.rs/agencije-za-nekretnine/277/",
      "izvor": "nrs"
    },
    {
      "id": "cf55da811c08",
      "url": "https://www.nekretnine.rs/oglasi/1133591/",
      "naslov": "Stan Ulica Omladinskih brigada 84g, Stari Aerodrom, Beograd",
      "opis": "BEL MONDO predstavlja sklad dinamične zajednice, bogate raznovrsnim sadržajima i prijatnim ambijentom koji pruža osećaj privatnosti i udobnosti. Smešten u centralnom delu Novog Beograda, sa",
      "zgrada": "Bel Mondo",
      "struktura": "5.0",
      "cena": null,
      "m2": 189.0,
      "cena_m2": null,
      "agencija": "Bel Mondo",
      "agencija_url": "https://www.nekretnine.rs/agencije-za-nekretnine/4845/",
      "izvor": "nrs"
    },
    {
      "id": "72adeb2d4e69",
      "url": "https://www.nekretnine.rs/oglasi/1015325/",
      "naslov": "Dvosobni stan Jurija Gagarina, Belvil, Beograd",
      "opis": "Uknjižen dvosoban stan, 68 m2, lux namešten, opremljen, velika terasa, 2 lifta, garaža, Belvil,blizina ZC Medigoup ,Novi Beograd</br>Izuzetan stan u ponudi za prodaju u vidjenom stanju.Stan je",
      "zgrada": "Belvil",
      "struktura": "2.0",
      "cena": 265000.0,
      "m2": 68.0,
      "cena_m2": 3897,
      "agencija": "KW CVETKOVIĆ ROŠKOV",
      "agencija_url": "https://www.nekretnine.rs/agencije-za-nekretnine/53/",
      "izvor": "nrs"
    },
    {
      "id": "5a50d2b04a83",
      "url": "https://www.nekretnine.rs/oglasi/1254463/",
      "naslov": "Dvosobni stan Jurija Gagarina, Mladost, Beograd",
      "opis": "Odlican za stanovanje i kao investicija. Stan je istocno orijentisan, veoma svetao i osuncan, sa obiljem prirodne svetlosti. Nalazi se u novoizgradjenom kompleksu \"Lastavice\" na Novom Beogradu, preko",
      "zgrada": "Lastavica",
      "struktura": "2.0",
      "cena": 199000.0,
      "m2": 39.0,
      "cena_m2": 5103,
      "agencija": "EUROPOLIS REAL ESTATE",
      "agencija_url": "https://www.nekretnine.rs/agencije-za-nekretnine/579/",
      "izvor": "nrs"
    },
    {
      "id": "d8a1df82c6e9",
      "url": "https://www.nekretnine.rs/oglasi/1250995/",
      "naslov": "Dvosobni stan Omladinskih brigada, Belvil, Beograd",
      "opis": "Na prodaju luksuzno opremljen dvosoban stan  West Kula, Beograd 399.900 eur\n\nProdaje se kompletno opremljen luksuzni stan površine 60m, po strukturi dvosoban, modernog i funkcionalnog dizajna.\n\nStan",
      "zgrada": "West 65 Kula",
      "struktura": "2.0",
      "cena": 399900.0,
      "m2": 60.0,
      "cena_m2": 6665,
      "agencija": "EUROPOLIS REAL ESTATE",
      "agencija_url": "https://www.nekretnine.rs/agencije-za-nekretnine/579/",
      "izvor": "nrs"
    },
    {
      "id": "47a14f9b2b83",
      "url": "https://www.nekretnine.rs/oglasi/1274339/",
      "naslov": "Trosobni stan Đorđa Stanojevića, Belvil, Beograd",
      "opis": "Retko u ponudi. Stan na atraktivnojj lokaciji u naselju Belvil. Po strukturi trosoban, komforan, dve spavace sobe, dva kupatila, ostava. Dobro pozicioniran, trostrano orjentisan. Dva garazna mesta uz",
      "zgrada": "Belvil",
      "struktura": "3.0",
      "cena": 399000.0,
      "m2": 107.0,
      "cena_m2": 3729,
      "agencija": "M REAL ESTATE",
      "agencija_url": "https://www.nekretnine.rs/agencije-za-nekretnine/15/",
      "izvor": "nrs"
    },
    {
      "id": "b9b1d5816f96",
      "url": "https://www.nekretnine.rs/oglasi/1047601/",
      "naslov": "Četvorosobni stan novo, četvrti sprat, Savski kej, Beograd",
      "opis": "Stan 83m2, 4-soban, u novoizgrađenom kompleksu \"Lastavice\". Odlične strukture i spratnosti, dvostrano orijentisan. Sastoji se od velikog dnevnog boravka sa trpezarijom i kuhinjom, iz koga se izlazi",
      "zgrada": "Lastavica",
      "struktura": "4.0",
      "cena": 390000.0,
      "m2": 83.0,
      "cena_m2": 4699,
      "agencija": null,
      "agencija_url": null,
      "izvor": "nrs"
    },
    {
      "id": "183bb44e08ab",
      "url": "https://www.nekretnine.rs/oglasi/1133497/",
      "naslov": "Stan Ulica Omladinskih brigada 84g, Stari Aerodrom, Beograd",
      "opis": "BEL MONDO predstavlja sklad dinamične zajednice, bogate raznovrsnim sadržajima i prijatnim ambijentom koji pruža osećaj privatnosti i udobnosti. Smešten u centralnom delu Novog Beograda, sa",
      "zgrada": "Bel Mondo",
      "struktura": "ostalo",
      "cena": null,
      "m2": 89.0,
      "cena_m2": null,
      "agencija": "Bel Mondo",
      "agencija_url": "https://www.nekretnine.rs/agencije-za-nekretnine/4845/",
      "izvor": "nrs"
    },
    {
      "id": "80c5f88e83f1",
      "url": "https://www.nekretnine.rs/oglasi/1255523/",
      "naslov": "Četvorosobni stan Tošin bunar, Stari Aerodrom, Beograd",
      "opis": "BEZ PROVIZIJE ZA KUPCA\nNew Minel Residence je novi biser moderne arhitektrure na Novom Beogradu. Stan poseduje 3 spavaće sobe, 2 mokra čvora, lođu, orijentisan je ka Tošinom bunaru. Centalno",
      "zgrada": "New Minel",
      "struktura": "4.0",
      "cena": 336937.0,
      "m2": 84.0,
      "cena_m2": 4011,
      "agencija": "ART NEKRETNINE",
      "agencija_url": "https://www.nekretnine.rs/agencije-za-nekretnine/241/",
      "izvor": "nrs"
    },
    {
      "id": "16dbe5899ce2",
      "url": "https://www.nekretnine.rs/oglasi/1254153/",
      "naslov": "Dvosobni stan Đorđa Stanojevića, Belvil, Beograd",
      "opis": " AIRPORT GARDEN  NOVOGRADNJA KOJA PRUŽA VIŠE OD STANA\n\nU ponudi je moderan stan površine 55 m sa pripadajućim parking mestom od 13 m na nivou -2 garaže .garažno mesto se doplacuje 35 000 e, u",
      "zgrada": "Airport Garden",
      "struktura": "2.0",
      "cena": 247500.0,
      "m2": 55.0,
      "cena_m2": 4500,
      "agencija": "Sandra Milenković PR Capitalrent nekretnine",
      "agencija_url": "https://www.nekretnine.rs/agencije-za-nekretnine/1353/",
      "izvor": "nrs"
    },
    {
      "id": "d8a8a9f60713",
      "url": "https://www.nekretnine.rs/oglasi/1269361/",
      "naslov": "Dvosobni stan Đorđa Stanojevića, Belvil, Beograd",
      "opis": "U ponudi je stan u novogradnji, naselje Airport garden.\n\nLuksuzan,dvosoban stan, u zgradi koja se gradi od najkvalitetnijih materijala.\nNalazi se na drugom spratu.\nLokacija je fenomenalna, naselje je",
      "zgrada": "Airport Garden",
      "struktura": "2.0",
      "cena": 228900.0,
      "m2": 56.0,
      "cena_m2": 4088,
      "agencija": "ART NEKRETNINE",
      "agencija_url": "https://www.nekretnine.rs/agencije-za-nekretnine/241/",
      "izvor": "nrs"
    },
    {
      "id": "6e0edd5bc4f0",
      "url": "https://www.nekretnine.rs/oglasi/1255483/",
      "naslov": "Četvorosobni stan Đorđa Stanojevića, Belvil, Beograd",
      "opis": "Na prodaju je stan u kompleksu Airport Garden, koji se nalazi iza tržnog centra Soul. Reč je o penthouse stanu na 12. spratu, poslednjem u zgradi, sa pogledom koji ostaje zauvek  nema mogućnosti",
      "zgrada": "Airport Garden",
      "struktura": "4.0",
      "cena": 550000.0,
      "m2": 134.0,
      "cena_m2": 4104,
      "agencija": "ART NEKRETNINE",
      "agencija_url": "https://www.nekretnine.rs/agencije-za-nekretnine/241/",
      "izvor": "nrs"
    },
    {
      "id": "2ca1333db7c5",
      "url": "https://www.nekretnine.rs/oglasi/37469/",
      "naslov": "Trosobni stan novo, prvi sprat, Belvil, Beograd",
      "opis": "U prodaji je izuzetna nekretnina u jednom od najtraženijih i  najuređenijih kompleksa na Novom Beogradu - A Blok, u ulici Jurija Gagarina. U pitanju je luksuzan trosoban stan ukupne površine 96",
      "zgrada": "A Blok",
      "struktura": "3.0",
      "cena": 377999.0,
      "m2": 96.0,
      "cena_m2": 3937,
      "agencija": "ALFA SISTEM NEKRETNINE",
      "agencija_url": "https://www.nekretnine.rs/agencije-za-nekretnine/685/",
      "izvor": "nrs"
    },
    {
      "id": "a0cf25001203",
      "url": "https://www.nekretnine.rs/oglasi/1264671/",
      "naslov": "Dvosobni stan Đorđa Stanojevića, Belvil, Beograd",
      "opis": "Novi Beograd, u izgradnji, više stanova , ulica Đorđa Stanojevića, objekat u izgradnji, useljiv novembra 2027-e godine .\nU cenu stana nije uključen PDV. \n Moderno projektovan objekat smešten na",
      "zgrada": "Belvil",
      "struktura": "2.0",
      "cena": 161842.0,
      "m2": 43.0,
      "cena_m2": 3764,
      "agencija": "FORMA TIM",
      "agencija_url": "https://www.nekretnine.rs/agencije-za-nekretnine/237/",
      "izvor": "nrs"
    },
    {
      "id": "154569db4319",
      "url": "https://www.nekretnine.rs/oglasi/1275411/",
      "naslov": "Dvosobni stan Jurija Gagarina, Belvil, Beograd",
      "opis": "Agencijski ID: 132455, IX/X, lift, terasa, uknjižen, garaza, parking, podrum, stambena zgrada. Na super lokaciji u Belvilu se prodaje dvosoban stan. Idealan za život kao i informacija. Više",
      "zgrada": "Belvil",
      "struktura": "2.0",
      "cena": 219000.0,
      "m2": 47.0,
      "cena_m2": 4660,
      "agencija": "BEOCITY NEKRETNINE",
      "agencija_url": "https://www.nekretnine.rs/agencije-za-nekretnine/307/",
      "izvor": "nrs"
    },
    {
      "id": "f1dca4409896",
      "url": "https://www.nekretnine.rs/oglasi/1187841/",
      "naslov": "Jednosoban stan Đorđa Stanojevića, Belvil, Beograd",
      "opis": "Stan je potpuno nov i sređen lux. Na korak do TC. Prodaje se namešten i super sređen i namešten. Spreman za investiciju ili život.   Prostorije: predsoblje, dnevna soba, ugradna kuhinja,",
      "zgrada": "Belvil",
      "struktura": "garsonjera",
      "cena": 183600.0,
      "m2": 32.0,
      "cena_m2": 5738,
      "agencija": "Lambrin nekretnine",
      "agencija_url": "https://www.nekretnine.rs/agencije-za-nekretnine/4791/",
      "izvor": "nrs"
    }
  ]
}